server_client/__init__.py
server_client/ai_client.py
server_client/client.py
server_client/main.py
server_client/server.py
server_client/start_server_with_ai_client.py
server_client/terminal_client.py
socktalk-0.2.3.dist-info/LICENSE
socktalk-0.2.3.dist-info/METADATA
socktalk-0.2.3.dist-info/WHEEL
socktalk-0.2.3.dist-info/entry_points.txt
socktalk-0.2.3.dist-info/top_level.txt
socktalk-0.2.3.dist-info/RECORD
