Metadata-Version: 2.1
Name: socktalk
Version: 0.2.3
Summary: Socket-based AI chat server and multi-user chat client
Project-URL: Source, https://github.com/mdkmk/socktalk
Keywords: chat server,chat client,AI chatbot,chatGPT,OPENAI API,socket programming,select.select(),multi-user chat,real-time communication,Python chat application
Classifier: Programming Language :: Python :: 3
Classifier: License :: OSI Approved :: Mozilla Public License 2.0 (MPL 2.0)
Classifier: Operating System :: OS Independent
Requires-Python: >=3.6
License-File: LICENSE
Requires-Dist: annotated-types ==0.6.0
Requires-Dist: anyio ==4.3.0
Requires-Dist: certifi ==2024.2.2
Requires-Dist: distro ==1.9.0
Requires-Dist: exceptiongroup ==1.2.0
Requires-Dist: h11 ==0.14.0
Requires-Dist: httpcore ==1.0.5
Requires-Dist: httpx ==0.27.0
Requires-Dist: idna ==3.7
Requires-Dist: openai ==1.14.2
Requires-Dist: pydantic ==2.6.4
Requires-Dist: pydantic-core ==2.16.3
Requires-Dist: PyQt5 ==5.15.10
Requires-Dist: PyQt5-Qt5 ==5.15.2
Requires-Dist: PyQt5-sip ==12.13.0
Requires-Dist: sniffio ==1.3.1
Requires-Dist: tqdm ==4.66.2
Requires-Dist: typing-extensions ==4.11.0
